{"cameraMode":{"drawMode":0,"name":"Shaded","section":"Shading Mode"},"sceneLighting":true,"audioPlay":false,"sceneViewState":{"m_AlwaysRefresh":false,"showFog":true,"showSkybox":true,"showFlares":true,"showImageEffects":true,"showParticleSystems":true,"showVisualEffectGraphs":true,"m_FxEnabled":true},"in2DMode":false,"pivot":{"x":34.97050857543945,"y":2.065836191177368,"z":14.540748596191407},"rotation":{"x":-0.6052365303039551,"y":0.17752008140087129,"z":-0.1408398300409317,"w":-0.7631739974021912},"size":10.056341171264649,"orthographic":false}